humanpass-1.0.0.dist-info/licenses/LICENSE
passgen/__init__.py
passgen/generator.py
passgen/tests/__init__.py
passgen/tests/test_generator.py
humanpass-1.0.0.dist-info/METADATA
humanpass-1.0.0.dist-info/WHEEL
humanpass-1.0.0.dist-info/top_level.txt
humanpass-1.0.0.dist-info/RECORD
