Metadata-Version: 2.4
Name: humanpass
Version: 1.0.0
Summary: This is a package for generating random secure passwords for humans.
Home-page: https://github.com/mwanjajoel/humanpass
Author: mwanjajoel
Author-email: joelsilverworks@gmail.com
License: MIT
Classifier: License :: OSI Approved :: MIT License
Classifier: Programming Language :: Python :: 3
Classifier: Programming Language :: Python :: 3.7
License-File: LICENSE
Dynamic: author
Dynamic: author-email
Dynamic: classifier
Dynamic: description
Dynamic: description-content-type
Dynamic: home-page
Dynamic: license
Dynamic: license-file
Dynamic: summary
